databricks/__init__.py
databricks/py.typed
databricks/labs/__init__.py
databricks/labs/bladespector/__about__.py
databricks/labs/bladespector/__init__.py
databricks/labs/bladespector/analyzer.py
databricks/labs/bladespector/Analyzer/Linux/analyzer
databricks/labs/bladespector/Analyzer/MacOS/analyzer
databricks/labs/bladespector/Analyzer/Windows/analyzer.exe
databricks_bb_analyzer-0.2.0.dist-info/METADATA
databricks_bb_analyzer-0.2.0.dist-info/WHEEL
databricks_bb_analyzer-0.2.0.dist-info/RECORD
