Metadata-Version: 2.4
Name: databricks-bb-analyzer
Version: 0.2.0
Summary: Lakebridge analyzer
Project-URL: Documentation, https://github.com/databrickslabs/bladerunner
Project-URL: Issues, https://github.com/databrickslabs/bladerunner/issues
Project-URL: Source, https://github.com/databrickslabs/bladerunner
Keywords: Analyzer,Databricks,Lakebridge
Classifier: Development Status :: 3 - Alpha
Classifier: Programming Language :: Python :: 3.10
Classifier: Programming Language :: Python :: Implementation :: CPython
Requires-Python: >=3.10
